modoboa_rspamd/__init__.py
modoboa_rspamd/admin.py
modoboa_rspamd/app_settings.py
modoboa_rspamd/apps.py
modoboa_rspamd/handlers.py
modoboa_rspamd/models.py
modoboa_rspamd/modo_extension.py
modoboa_rspamd/tests.py
modoboa_rspamd/views.py
modoboa_rspamd/api/__init__.py
modoboa_rspamd/api/v2/__init__.py
modoboa_rspamd/api/v2/serializers.py
modoboa_rspamd/locale/br/LC_MESSAGES/django.mo
modoboa_rspamd/locale/br/LC_MESSAGES/django.po
modoboa_rspamd/locale/cs/LC_MESSAGES/django.mo
modoboa_rspamd/locale/cs/LC_MESSAGES/django.po
modoboa_rspamd/locale/cs_CZ/LC_MESSAGES/django.mo
modoboa_rspamd/locale/cs_CZ/LC_MESSAGES/django.po
modoboa_rspamd/locale/de/LC_MESSAGES/django.mo
modoboa_rspamd/locale/de/LC_MESSAGES/django.po
modoboa_rspamd/locale/de_DE/LC_MESSAGES/django.mo
modoboa_rspamd/locale/de_DE/LC_MESSAGES/django.po
modoboa_rspamd/locale/el_GR/LC_MESSAGES/django.mo
modoboa_rspamd/locale/el_GR/LC_MESSAGES/django.po
modoboa_rspamd/locale/en/LC_MESSAGES/django.mo
modoboa_rspamd/locale/en/LC_MESSAGES/django.po
modoboa_rspamd/locale/es/LC_MESSAGES/django.mo
modoboa_rspamd/locale/es/LC_MESSAGES/django.po
modoboa_rspamd/locale/fi/LC_MESSAGES/django.mo
modoboa_rspamd/locale/fi/LC_MESSAGES/django.po
modoboa_rspamd/locale/fr/LC_MESSAGES/django.mo
modoboa_rspamd/locale/fr/LC_MESSAGES/django.po
modoboa_rspamd/locale/hu/LC_MESSAGES/django.mo
modoboa_rspamd/locale/hu/LC_MESSAGES/django.po
modoboa_rspamd/locale/it/LC_MESSAGES/django.mo
modoboa_rspamd/locale/it/LC_MESSAGES/django.po
modoboa_rspamd/locale/ja_JP/LC_MESSAGES/django.mo
modoboa_rspamd/locale/ja_JP/LC_MESSAGES/django.po
modoboa_rspamd/locale/ka/LC_MESSAGES/django.mo
modoboa_rspamd/locale/ka/LC_MESSAGES/django.po
modoboa_rspamd/locale/nl_NL/LC_MESSAGES/django.mo
modoboa_rspamd/locale/nl_NL/LC_MESSAGES/django.po
modoboa_rspamd/locale/no/LC_MESSAGES/django.mo
modoboa_rspamd/locale/no/LC_MESSAGES/django.po
modoboa_rspamd/locale/pl_PL/LC_MESSAGES/django.mo
modoboa_rspamd/locale/pl_PL/LC_MESSAGES/django.po
modoboa_rspamd-1.0.0.dist-info/LICENSE
modoboa_rspamd-1.0.0.dist-info/METADATA
modoboa_rspamd-1.0.0.dist-info/WHEEL
modoboa_rspamd-1.0.0.dist-info/top_level.txt
modoboa_rspamd-1.0.0.dist-info/RECORD
