Metadata-Version: 2.1
Name: modoboa-rspamd
Version: 1.0.0
Summary: The rspamd frontend of Modoboa
Home-page: http://modoboa.org/
Author: Antoine Nguyen
Author-email: Antoine Nguyen <tonio@ngyn.org>
License: The MIT License (MIT)
Project-URL: homepage, http://modoboa.org/
Project-URL: documentation, https://modoboa-rspamd.readthedocs.io/en/latest/
Project-URL: repository, https://github.com/modoboa/modoboa-rspamd
Keywords: email
Classifier: Development Status :: 5 - Production/Stable
Classifier: Environment :: Web Environment
Classifier: Framework :: Django :: 4.2
Classifier: Intended Audience :: System Administrators
Classifier: License :: OSI Approved :: MIT License
Classifier: Operating System :: OS Independent
Classifier: Programming Language :: Python :: 3.8
Classifier: Programming Language :: Python :: 3.9
Classifier: Programming Language :: Python :: 3.10
Classifier: Programming Language :: Python :: 3.11
Classifier: Topic :: Communications :: Email
Classifier: Topic :: Internet :: WWW/HTTP
Requires-Python: >=3.8
License-File: LICENSE
Requires-Dist: modoboa >=2.2.0
